qiskit_metal/__init__.py
qiskit_metal/_defaults.py
qiskit_metal/_is_design.py
qiskit_metal/config.py
qiskit_metal/_gui/__init__.py
qiskit_metal/_gui/component_widget_ui.py
qiskit_metal/_gui/component_widget_ui.ui
qiskit_metal/_gui/elements_ui.py
qiskit_metal/_gui/elements_ui.ui
qiskit_metal/_gui/elements_window.py
qiskit_metal/_gui/endcap_hfss_gui.py
qiskit_metal/_gui/endcap_hfss_ui.py
qiskit_metal/_gui/endcap_hfss_ui.ui
qiskit_metal/_gui/endcap_q3d_gui.py
qiskit_metal/_gui/endcap_q3d_ui.py
qiskit_metal/_gui/endcap_q3d_ui.ui
qiskit_metal/_gui/list_model_base.py
qiskit_metal/_gui/main_window.py
qiskit_metal/_gui/main_window_base.py
qiskit_metal/_gui/main_window_rc.qrc
qiskit_metal/_gui/main_window_rc_rc.py
qiskit_metal/_gui/main_window_ui.py
qiskit_metal/_gui/main_window_ui.ui
qiskit_metal/_gui/net_list_ui.py
qiskit_metal/_gui/net_list_ui.ui
qiskit_metal/_gui/net_list_window.py
qiskit_metal/_gui/plot_window_ui.py
qiskit_metal/_gui/plot_window_ui.ui
qiskit_metal/_gui/renderer_gds_gui.py
qiskit_metal/_gui/renderer_gds_model.py
qiskit_metal/_gui/renderer_gds_ui.py
qiskit_metal/_gui/renderer_gds_ui.ui
qiskit_metal/_gui/renderer_hfss_gui.py
qiskit_metal/_gui/renderer_hfss_model.py
qiskit_metal/_gui/renderer_hfss_ui.py
qiskit_metal/_gui/renderer_hfss_ui.ui
qiskit_metal/_gui/renderer_q3d_gui.py
qiskit_metal/_gui/renderer_q3d_model.py
qiskit_metal/_gui/renderer_q3d_ui.py
qiskit_metal/_gui/renderer_q3d_ui.ui
qiskit_metal/_gui/tree_view_base.py
qiskit_metal/_gui/_imgs/browser.png
qiskit_metal/_gui/_imgs/build_history.png
qiskit_metal/_gui/_imgs/build_history_small.png
qiskit_metal/_gui/_imgs/cancel.png
qiskit_metal/_gui/_imgs/delete.png
qiskit_metal/_gui/_imgs/drawing.png
qiskit_metal/_gui/_imgs/force_refresh.png
qiskit_metal/_gui/_imgs/frequency.png
qiskit_metal/_gui/_imgs/icon_attributions.txt
qiskit_metal/_gui/_imgs/lightbulb.png
qiskit_metal/_gui/_imgs/log copy.png
qiskit_metal/_gui/_imgs/log.png
qiskit_metal/_gui/_imgs/metal_logo.png
qiskit_metal/_gui/_imgs/painting.png
qiskit_metal-0.1.2.dist-info/LICENSE.txt
qiskit_metal-0.1.2.dist-info/METADATA
qiskit_metal-0.1.2.dist-info/WHEEL
qiskit_metal-0.1.2.dist-info/top_level.txt
qiskit_metal-0.1.2.dist-info/RECORD
