Metadata-Version: 2.1
Name: qiskit-metal
Version: 0.1.2
Summary: Qiskit Metal | for quantum device design & analysis
Home-page: https://github.com/Qiskit/qiskit-metal
Author: Qiskit Metal Development Team
Author-email: qiskit@qiskit.org
License: Apache 2.0
Project-URL: Bug Tracker, https://github.com/Qiskit/qiskit-metal/issues
Project-URL: Documentation, https://qiskit.org/documentation/metal
Project-URL: Source Code, https://github.com/Qiskit/qiskit-metal
Keywords: qiskit sdk quantum eda
Platform: UNKNOWN
Classifier: License :: OSI Approved :: Apache Software License
Classifier: Intended Audience :: Developers
Classifier: Intended Audience :: Science/Research
Classifier: Operating System :: Microsoft :: Windows
Classifier: Operating System :: MacOS
Classifier: Operating System :: POSIX :: Linux
Classifier: Programming Language :: Python :: 3 :: Only
Classifier: Programming Language :: Python :: 3.7
Classifier: Programming Language :: Python :: 3.8
Classifier: Programming Language :: Python :: 3.9
Classifier: Topic :: Scientific/Engineering
Requires-Python: >=3.7
Requires-Dist: addict
Requires-Dist: descartes
Requires-Dist: gdspy (>=1.5.2)
Requires-Dist: ipython
Requires-Dist: matplotlib
Requires-Dist: numpy
Requires-Dist: pandas
Requires-Dist: pint
Requires-Dist: pyEPR-quantum (>=0.8.5.7)
Requires-Dist: pygments
Requires-Dist: pyside2
Requires-Dist: qutip
Requires-Dist: scipy
Requires-Dist: shapely
Requires-Dist: scqubits
Requires-Dist: geopandas ; platform_system != "Windows"
